as3toplevel.py
as3toplevel-0.0.4.dist-info/LICENSE
as3toplevel-0.0.4.dist-info/METADATA
as3toplevel-0.0.4.dist-info/WHEEL
as3toplevel-0.0.4.dist-info/top_level.txt
as3toplevel-0.0.4.dist-info/RECORD
