Metadata-Version: 2.1
Name: as3toplevel
Version: 0.0.4
Summary: Python implementation of the ActionScript3 toplevel
Home-page: https://github.com/ajdelguidice/python-as3toplevel
Author: ajdelguidice
Author-email: ajdelguidice@gmail.com
Classifier: Development Status :: 4 - Beta
Classifier: License :: OSI Approved :: MIT License
Classifier: Operating System :: OS Independent
Classifier: Programming Language :: Python :: 3.8
Classifier: Topic :: Utilities
Requires-Python: >=3.8
License-File: LICENSE
Requires-Dist: numpy
